{"asistencia": {"asistencia": [{"clasificado": true, "distance": 0.2784, "id": "2", "message": "Se identifico correctamente al usuario.", "rol": "alumno", "hora_detectado": "17:07:23"}, {"clasificado": true, "distance": 0.3079, "id": "2", "message": "Se identifico correctamente al usuario.", "rol": "alumno", "hora_detectado": "17:07:29"}, {"clasificado": true, "distance": 0.2469, "id": "2", "message": "Se identifico correctamente al usuario.", "rol": "alumno", "hora_detectado": "17:07:34"}, {"clasificado": true, "distance": 0.2275, "id": "2", "message": "Se identifico correctamente al usuario.", "rol": "alumno", "hora_detectado": "17:07:39"}, {"clasificado": true, "distance": 0.2822, "id": "2", "message": "Se identifico correctamente al usuario.", "rol": "alumno", "hora_detectado": "17:07:44"}, {"clasificado": true, "distance": 0.2326, "id": "2", "message": "Se identifico correctamente al usuario.", "rol": "alumno", "hora_detectado": "17:07:49"}, {"clasificado": true, "distance": 0.338, "id": "2", "message": "Se identifico correctamente al usuario.", "rol": "alumno", "hora_detectado": "17:07:56"}, {"clasificado": true, "distance": 0.3936, "id": "2", "message": "Se identifico correctamente al usuario.", "rol": "alumno", "hora_detectado": "17:08:07"}, {"clasificado": true, "distance": 0.2342, "id": "2", "message": "Se identifico correctamente al usuario.", "rol": "alumno", "hora_detectado": "17:37:56"}, {"clasificado": true, "distance": 0.2594, "id": "2", "message": "Se identifico correctamente al usuario.", "rol": "alumno", "hora_detectado": "17:39:42"}]}}